odoo/addons/account_clearance_plan/README.rst
odoo/addons/account_clearance_plan/__init__.py
odoo/addons/account_clearance_plan/__manifest__.py
odoo/addons/account_clearance_plan/i18n/account_clearance_plan.pot
odoo/addons/account_clearance_plan/models/__init__.py
odoo/addons/account_clearance_plan/models/account_invoice.py
odoo/addons/account_clearance_plan/models/res_company.py
odoo/addons/account_clearance_plan/models/res_config_settings.py
odoo/addons/account_clearance_plan/readme/CONTRIBUTORS.rst
odoo/addons/account_clearance_plan/readme/DESCRIPTION.rst
odoo/addons/account_clearance_plan/readme/ROADMAP.rst
odoo/addons/account_clearance_plan/readme/USAGE.rst
odoo/addons/account_clearance_plan/static/description/icon.png
odoo/addons/account_clearance_plan/static/description/index.html
odoo/addons/account_clearance_plan/tests/__init__.py
odoo/addons/account_clearance_plan/tests/test_account_clearance_plan.py
odoo/addons/account_clearance_plan/views/res_config_settings.xml
odoo/addons/account_clearance_plan/wizard/__init__.py
odoo/addons/account_clearance_plan/wizard/account_clearance_plan.py
odoo/addons/account_clearance_plan/wizard/account_clearance_plan_wizard.xml
odoo12_addon_account_clearance_plan-12.0.1.0.1.dist-info/METADATA
odoo12_addon_account_clearance_plan-12.0.1.0.1.dist-info/WHEEL
odoo12_addon_account_clearance_plan-12.0.1.0.1.dist-info/top_level.txt
odoo12_addon_account_clearance_plan-12.0.1.0.1.dist-info/RECORD
