Metadata-Version: 2.1
Name: odoo12-addon-account-clearance-plan
Version: 12.0.1.0.1
Summary: This addon allows to define clearance plans in order to reorganize debts (own and customers' ones).
Home-page: https://github.com/OCA/account-financial-tools
Author: ACSONE SA/NV, Odoo Community Association (OCA)
Author-email: support@odoo-community.org
License: AGPL-3
Platform: UNKNOWN
Classifier: Programming Language :: Python
Classifier: Framework :: Odoo
Classifier: License :: OSI Approved :: GNU Affero General Public License v3
Requires-Python: >=3.5
Requires-Dist: odoo (<12.1dev,>=12.0a)
